nova/tests/unit/virt/lxd/__init__.py
nova/tests/unit/virt/lxd/fake_api.py
nova/tests/unit/virt/lxd/stubs.py
nova/tests/unit/virt/lxd/test_common.py
nova/tests/unit/virt/lxd/test_driver.py
nova/tests/unit/virt/lxd/test_flavor.py
nova/tests/unit/virt/lxd/test_migrate.py
nova/tests/unit/virt/lxd/test_session.py
nova/tests/unit/virt/lxd/test_storage.py
nova/tests/unit/virt/lxd/test_vif.py
nova/virt/lxd/__init__.py
nova/virt/lxd/common.py
nova/virt/lxd/driver.py
nova/virt/lxd/flavor.py
nova/virt/lxd/session.py
nova/virt/lxd/storage.py
nova/virt/lxd/vif.py
nova_lxd_tempest_plugin/README
nova_lxd_tempest_plugin/__init__.py
nova_lxd_tempest_plugin/plugin.py
nova_lxd_tempest_plugin/tests/__init__.py
nova_lxd_tempest_plugin/tests/api/__init__.py
nova_lxd_tempest_plugin/tests/api/compute/__init__.py
nova_lxd_tempest_plugin/tests/api/compute/servers/__init__.py
nova_lxd_tempest_plugin/tests/api/compute/servers/test_create_server.py
nova_lxd_tempest_plugin/tests/api/compute/servers/test_servers.py
nova_lxd_tempest_plugin/tests/api/compute/volumes/__init__.py
nova_lxd_tempest_plugin/tests/api/compute/volumes/test_attach_volume.py
nova_lxd_tempest_plugin/tests/scenario/__init__.py
nova_lxd_tempest_plugin/tests/scenario/manager.py
nova_lxd_tempest_plugin/tests/scenario/test_server_basic_ops.py
nova_lxd_tempest_plugin/tests/scenario/test_volume_ops.py
nova_lxd-19.0.0.dist-info/AUTHORS
nova_lxd-19.0.0.dist-info/LICENSE
nova_lxd-19.0.0.dist-info/METADATA
nova_lxd-19.0.0.dist-info/WHEEL
nova_lxd-19.0.0.dist-info/entry_points.txt
nova_lxd-19.0.0.dist-info/pbr.json
nova_lxd-19.0.0.dist-info/top_level.txt
nova_lxd-19.0.0.dist-info/RECORD
