Metadata-Version: 2.1
Name: nova-lxd
Version: 19.0.0
Summary: native lxd driver for openstack
Home-page: https://www.openstack.org/
Author: OpenStack
Author-email: openstack-discuss@lists.openstack.org
License: UNKNOWN
Platform: UNKNOWN
Classifier: Environment :: OpenStack
Classifier: Intended Audience :: Information Technology
Classifier: Intended Audience :: System Administrators
Classifier: License :: OSI Approved :: Apache Software License
Classifier: Operating System :: POSIX :: Linux
Classifier: Programming Language :: Python
Classifier: Programming Language :: Python :: 2
Classifier: Programming Language :: Python :: 2.7
Requires-Dist: pbr (!=2.1.0,>=3.1.1)
Requires-Dist: os-brick (>=2.3.0)
Requires-Dist: os-vif (!=1.8.0,>=1.9.0)
Requires-Dist: oslo.config (>=5.2.0)
Requires-Dist: oslo.concurrency (>=3.26.0)
Requires-Dist: oslo.utils (>=3.36.0)
Requires-Dist: oslo.i18n (>=3.20.0)
Requires-Dist: oslo.log (>=3.37.0)
Requires-Dist: pylxd (>=2.2.6)
